{
  "users": [
    {
      "name": "fefe",
      "age": "greg",
      "id": 2
    }
  ],
  "products": [
    {
      "id": 1,
      "title": "Mobil SUPER 3000 X1 5W-40, 1 л. Масло моторное.",
      "price": "2 864",
      "salePrice": "2 334",
      "code": 153798,
      "img": "https://github.com/Nuriddin-coder/oner-img/blob/main/imgs/Recomend/rec-img-1.png?raw=true"
    },
    {
      "id": 2,
      "title": "Mobil SUPER 3000 X1 5W-40, 1 л. Масло моторное.",
      "price": "1200",
      "salePrice": "1000",
      "code": 153798,
      "img": "https://github.com/Nuriddin-coder/oner-img/blob/main/imgs/Recomend/rec-img-2.png?raw=true"
    },
    {
      "id": 3,
      "title": "Mobil SUPER 3000 X1 5W-40, 1 л. Масло моторное.",
      "price": "9300",
      "salePrice": "8900",
      "code": 153798,
      "img": "https://github.com/Nuriddin-coder/oner-img/blob/main/imgs/Recomend/rec-img-3.png?raw=true"
    },
    {
      "id": 4,
      "title": "Mobil SUPER 3000 X1 5W-40, 1 л. Масло моторное.",
      "price": "5000",
      "salePrice": "4600",
      "code": 153798,
      "img": "https://github.com/Nuriddin-coder/oner-img/blob/main/imgs/Recomend/rec-img-4.png?raw=true"
    },
    {
      "id": 5,
      "title": "Mobil SUPER 3000 X1 5W-40, 1 л. Масло моторное.",
      "price": "5000",
      "salePrice": "4600",
      "code": 153798,
      "img": "https://github.com/Nuriddin-coder/oner-img/blob/main/imgs/Disks/disk-img-1.png?raw=true"
    },
    {
      "id": 6,
      "title": "Mobil SUPER 3000 X1 5W-40, 1 л. Масло моторное.",
      "price": "5000",
      "salePrice": "4600",
      "code": 153798,
      "img": "https://github.com/Nuriddin-coder/oner-img/blob/main/imgs/Recomend/rec-img-2.png?raw=true"
    },
    {
      "id": 7,
      "title": "Mobil SUPER 3000 X1 5W-40, 1 л. Масло моторное.",
      "price": "5000",
      "salePrice": "4600",
      "code": 153798,
      "img": "https://github.com/Nuriddin-coder/oner-img/blob/main/imgs/Disks/disk-img-2.png?raw=true"
    },
    {
      "id": 8,
      "title": "Mobil SUPER 3000 X1 5W-40, 1 л. Масло моторное.",
      "price": "5000",
      "salePrice": "4600",
      "code": 153798,
      "img": "https://github.com/Nuriddin-coder/oner-img/blob/main/imgs/Recomend/rec-img-4.png?raw=true"
    },
    {
      "id": 9,
      "title": "Mobil SUPER 3000 X1 5W-40, 1 л. Масло моторное.",
      "price": "5000",
      "salePrice": "4600",
      "code": 153798,
      "img": "https://github.com/Nuriddin-coder/oner-img/blob/main/imgs/Recomend/rec-img-1.png?raw=true"
    },
    {
      "id": 10,
      "title": "Mobil SUPER 3000 X1 5W-40, 1 л. Масло моторное.",
      "price": "5000",
      "salePrice": "4600",
      "code": 153798,
      "img": "https://github.com/Nuriddin-coder/oner-img/blob/main/imgs/Disks/disk-img-3.png?raw=true"
    },
    {
      "id": 11,
      "title": "Mobil SUPER 3000 X1 5W-40, 1 л. Масло моторное.",
      "price": "5000",
      "salePrice": "4600",
      "code": 153798,
      "img": "https://github.com/Nuriddin-coder/oner-img/blob/main/imgs/Recomend/rec-img-4.png?raw=true"
    },
    {
      "id": 12,
      "title": "Mobil SUPER 3000 X1 5W-40, 1 л. Масло моторное.",
      "price": "5000",
      "salePrice": "4600",
      "code": 153798,
      "img": "https://github.com/Nuriddin-coder/oner-img/blob/main/imgs/Disks/disk-img-4.png?raw=true"
    },
    {
      "id": 13,
      "title": "Mobil SUPER 3000 X1 5W-40, 1 л. Масло моторное.",
      "price": "5000",
      "salePrice": "4600",
      "code": 153798,
      "img": "https://github.com/Nuriddin-coder/oner-img/blob/main/imgs/Recomend/rec-img-4.png?raw=true"
    },
    {
      "id": 14,
      "title": "Mobil SUPER 3000 X1 5W-40, 1 л. Масло моторное.",
      "price": "5000",
      "salePrice": "4600",
      "code": 153798,
      "img": "https://github.com/Nuriddin-coder/oner-img/blob/main/imgs/Recomend/rec-img-1.png?raw=true"
    },
    {
      "id": 15,
      "title": "Mobil SUPER 3000 X1 5W-40, 1 л. Масло моторное.",
      "price": "5000",
      "salePrice": "4600",
      "code": 153798,
      "img": "https://github.com/Nuriddin-coder/oner-img/blob/main/imgs/Recomend/rec-img-3.png?raw=true"
    },
    {
      "id": 16,
      "title": "Mobil SUPER 3000 X1 5W-40, 1 л. Масло моторное.",
      "price": "5000",
      "salePrice": "4600",
      "code": 153798,
      "img": "https://github.com/Nuriddin-coder/oner-img/blob/main/imgs/Disks/disk-img-2.png?raw=true"
    },
    {
      "id": 17,
      "title": "Mobil SUPER 3000 X1 5W-40, 1 л. Масло моторное.",
      "price": "5000",
      "salePrice": "4600",
      "code": 153798,
      "img": "https://github.com/Nuriddin-coder/oner-img/blob/main/imgs/Recomend/rec-img-2.png?raw=true"
    },
    {
      "id": 18,
      "title": "Mobil SUPER 3000 X1 5W-40, 1 л. Масло моторное.",
      "price": "5000",
      "salePrice": "4600",
      "code": 153798,
      "img": "https://github.com/Nuriddin-coder/oner-img/blob/main/imgs/Recomend/rec-img-4.png?raw=true"
    },
    {
      "id": 19,
      "title": "Mobil SUPER 3000 X1 5W-40, 1 л. Масло моторное.",
      "price": "5000",
      "salePrice": "4600",
      "code": 153798,
      "img": "https://github.com/Nuriddin-coder/oner-img/blob/main/imgs/Recomend/rec-img-2.png?raw=true"
    },
    {
      "id": 29,
      "title": "Mobil SUPER 3000 X1 5W-40, 1 л. Масло моторное.",
      "price": "5000",
      "salePrice": "4600",
      "code": 153798,
      "img": "https://github.com/Nuriddin-coder/oner-img/blob/main/imgs/Disks/disk-img-1.png?raw=true"
    }
  ]
}
